ngsolve_jupyterlab_widgets/__init__.py
ngsolve_jupyterlab_widgets/_frontend.py
ngsolve_jupyterlab_widgets/_version.py
ngsolve_jupyterlab_widgets/example.py
ngsolve_jupyterlab_widgets/nbextension/__init__.py
ngsolve_jupyterlab_widgets/nbextension/static/extension.js
ngsolve_jupyterlab_widgets/nbextension/static/index.js
ngsolve_jupyterlab_widgets/nbextension/static/index.js.map
ngsolve_jupyterlab_widgets/tests/__init__.py
ngsolve_jupyterlab_widgets/tests/conftest.py
ngsolve_jupyterlab_widgets/tests/test_example.py
ngsolve_jupyterlab_widgets/tests/test_nbextension_path.py
ngsolve_jupyterlab_widgets-0.1.10.data/data/etc/jupyter/nbconfig/notebook.d/ngsolve_jupyterlab_widgets.json
ngsolve_jupyterlab_widgets-0.1.10.data/data/share/jupyter/lab/extensions/ngsolve_jupyterlab_widgets-0.1.10.tgz
ngsolve_jupyterlab_widgets-0.1.10.data/data/share/jupyter/nbextensions/ngsolve_jupyterlab_widgets/extension.js
ngsolve_jupyterlab_widgets-0.1.10.data/data/share/jupyter/nbextensions/ngsolve_jupyterlab_widgets/index.js
ngsolve_jupyterlab_widgets-0.1.10.data/data/share/jupyter/nbextensions/ngsolve_jupyterlab_widgets/index.js.map
ngsolve_jupyterlab_widgets-0.1.10.dist-info/LICENSE.txt
ngsolve_jupyterlab_widgets-0.1.10.dist-info/METADATA
ngsolve_jupyterlab_widgets-0.1.10.dist-info/WHEEL
ngsolve_jupyterlab_widgets-0.1.10.dist-info/top_level.txt
ngsolve_jupyterlab_widgets-0.1.10.dist-info/RECORD
